Workbook

Sheet Leer_primero
A1: Proyecto | B1: BancoERP - Nexus · Entrega 3: Ejecución, gestión de defectos y cierre del STLC
A2: Equipo | B2: Luis Contreras (Líder QA) · Walter Rosales (QA Funcional) · Anderson Ariana (QA Técnico) · Sergio Och (QA Datos)
A3: Celdas a llenar | B3: Las celdas AMARILLAS: en Log_Ejecucion (Fecha, Resultado_Obtenido, Estado, ID_Defecto, Evidencia), en Bug_Tracker (filas nuevas), en Criterios_Salida (Regresión y aceptación del PO) y en Veredicto (veredicto individual).
A4: Celdas calculadas | B4: Las celdas VERDES se calculan solas: RTM_Final (resultado por REQ), Metricas_TSR, Criterios_Salida (valor y estado) y el veredicto final.
A5: Estados válidos | B5: Pass · Fail · Blocked · Skipped · Pendiente (lista desplegable). Todo Fail debe tener ID_Defecto y una fila en Bug_Tracker.
A6: Ejemplo de llenado (NO es un resultado real) | B6: Fecha: 20/10/2026 · Resultado_Obtenido: HTTP 401 "Credenciales incorrectas. Intento 1 de 5." · Estado: Pass · ID_Defecto: N/A · Evidencia: Postman TC-REQ01-002 / captura opcional
A7: Ejemplo de un Fail (NO es un resultado real) | B7: Resultado_Obtenido: HTTP 200 y el retiro se procesó · Estado: Fail · ID_Defecto: BUG-NEX-02 · Evidencia: Capturas_Bugs/Evidencia_BUG02_Sergio.png
A8: Fuente | B8: Casos, datos y criterios provienen del Master Test Plan (E1) y del Documento de Diseño e Implementación (E2).
A9: Ciclos de ejecución | B9: Log_Ejecucion contiene el ciclo 2 (22/10/2026, build corregida) y alimenta métricas, criterios y veredicto. El ciclo 1 (19/10/2026, NO-GO) se conserva sin cambios en Log_Ciclo1_19-10 y en el acta histórica de la hoja Veredicto.

Sheet Verificacion_STLC
A1: Fase_STLC | B1: Entregable_Clave | C1: Criterio_Verificado | D1: Estado_Cumplimiento | E1: Especialista_QA_Responsable
A2: Fase 1: Planificación | B2: Master Test Plan (E1) | C2: Alcance y criterios de entrada/salida definidos; 6 de 6 criterios de entrada evaluados | D2: Cumplido | E2: Luis Contreras
A3: Fase 2: Análisis | B3: RTM base (E1) y actualizada (E2) | C3: 18 de 18 requerimientos revisados y trazados a casos | D3: Cumplido | E3: Walter Rosales
A4: Fase 3: Diseño | B4: Repositorio de casos — Formato 1 (E2) | C4: 46 casos con las 5 técnicas de caja negra | D4: Cumplido | E4: Walter Rosales / Anderson Ariana
A5: Fase 4: Implementación | B5: Informe de Readiness — Formato 2 (E2) | C5: Ambiente QA aislado (RD-01..RD-15) y Mock Data sintética cargada | D5: Cumplido (RD-16 cerrado el 19/10/2026: Checklist_DB_Nexus.txt, 13/13 ok) | E5: Anderson Ariana / Sergio Och

Sheet Criterios_Entrada_MTP
A1: Criterio (MTP) | B1: Condición verificable | C1: Estado | D1: Evidencia | E1: Responsable
A2: Ambiente disponible | B2: Frontend, InternalAPI, PublicAPI y PostgreSQL de QA levantan sin errores; /api/ping y /api/home responden; Swagger accesible | C2: Cumplido | D2: RD-01..RD-04 (06/10/2026) | E2: Anderson Ariana
A3: Build disponible | B3: Baseline identificable (commit/tag) y build compila en Docker | C3: Cumplido | D3: Commit 28f3faf; imágenes internal-api/public-api corriendo (RD-01, RD-06 image_id) | E3: Luis Contreras
A4: Requerimientos revisados | B4: 100% de REQ-01..REQ-18 revisados y hallazgos críticos elevados | C4: Cumplido | D4: MTP E1: Formato 16 (hallazgos H-01..H-08); E2 sección 5 | E4: Luis Contreras
A5: Datos preparados | B5: Usuarios por rol, clientes sintéticos, cuentas por estado/tipo, caja, bancos ACH y fronteras sin datos reales | C5: Cumplido | D5: Carga base RD-05; capa Nexus cargada y checklist C-01..C-13 en ok = t (Checklist_DB_Nexus.txt, 19/10/2026) | E5: Sergio Och
A6: Configuración de seguridad congelada | B6: Intentos fallidos, expiración JWT/refresh/recuperación y política de contraseña registrados | C6: Cumplido | D6: E2 sección 1.2 = docker-compose.qa.yml (5 / 1 h / 7 d / 2 h / 5) | E6: Anderson Ariana
A7: Seeds/dependencias validados | B7: Catálogos, tipos de cuenta, plan contable y entidades de SPs cargados | C7: Cumplido | D7: C-08 plan 1101/2101/2102 activo y C-09 tipos AHORRO/MONETARIA (Checklist_DB_Nexus.txt, 19/10/2026) | E7: Sergio Och

Sheet RTM_Final
A1: REQ | B1: Prioridad_E1 | C1: Riesgo | D1: Casos | E1: Tecnicas | F1: Modulo | G1: Especialista_QA | H1: Casos_total | I1: Pass | J1: Fail | K1: Blocked | L1: Pendientes | M1: Resultado_REQ
A2: REQ-01 | B2: Crítica | C2: R-02 | D2: TC-REQ01-001, TC-REQ01-002, TC-REQ01-003 | E2: Análisis de Valores Límite; Partición de Equivalencia; Tabla de Decisión | F2: Seguridad y sesiones | G2: Anderson Ariana | H2: =COUNTIF(Log_Ejecucion!$B$2:$B$47,A2) | I2: =COUNTIFS(Log_Ejecucion!$B$2:$B$47,A2,Log_Ejecucion!$J$2:$J$47,"Pass") | J2: =COUNTIFS(Log_Ejecucion!$B$2:$B$47,A2,Log_Ejecucion!$J$2:$J$47,"Fail") | K2: =COUNTIFS(Log_Ejecucion!$B$2:$B$47,A2,Log_Ejecucion!$J$2:$J$47,"Blocked") | L2: =COUNTIFS(Log_Ejecucion!$B$2:$B$47,A2,Log_Ejecucion!$J$2:$J$47,"Pendiente") | M2: =IF(L2=H2,"Pendiente",IF(J2>0,"Con fallos",IF(I2=H2,"Aprobado","Parcial")))
A3: REQ-02 | B3: Crítica | C3: R-02 | D3: TC-REQ02-001, TC-REQ02-002 | E3: Transición de Estados | F3: Seguridad y sesiones | G3: Anderson Ariana | H3: =COUNTIF(Log_Ejecucion!$B$2:$B$47,A3) | I3: =COUNTIFS(Log_Ejecucion!$B$2:$B$47,A3,Log_Ejecucion!$J$2:$J$47,"Pass") | J3: =COUNTIFS(Log_Ejecucion!$B$2:$B$47,A3,Log_Ejecucion!$J$2:$J$47,"Fail") | K3: =COUNTIFS(Log_Ejecucion!$B$2:$B$47,A3,Log_Ejecucion!$J$2:$J$47,"Blocked") | L3: =COUNTIFS(Log_Ejecucion!$B$2:$B$47,A3,Log_Ejecucion!$J$2:$J$47,"Pendiente") | M3: =IF(L3=H3,"Pendiente",IF(J3>0,"Con fallos",IF(I3=H3,"Aprobado","Parcial")))
A4: REQ-03 | B4: Crítica | C4: R-01 | D4: TC-REQ03-001, TC-REQ03-002 | E4: Pairwise | F4: Seguridad y sesiones | G4: Anderson Ariana | H4: =COUNTIF(Log_Ejecucion!$B$2:$B$47,A4) | I4: =COUNTIFS(Log_Ejecucion!$B$2:$B$47,A4,Log_Ejecucion!$J$2:$J$47,"Pass") | J4: =COUNTIFS(Log_Ejecucion!$B$2:$B$47,A4,Log_Ejecucion!$J$2:$J$47,"Fail") | K4: =COUNTIFS(Log_Ejecucion!$B$2:$B$47,A4,Log_Ejecucion!$J$2:$J$47,"Blocked") | L4: =COUNTIFS(Log_Ejecucion!$B$2:$B$47,A4,Log_Ejecucion!$J$2:$J$47,"Pendiente") | M4: =IF(L4=H4,"Pendiente",IF(J4>0,"Con fallos",IF(I4=H4,"Aprobado","Parcial")))
A5: REQ-04 | B5: Alta | C5: R-09 | D5: TC-REQ04-001, TC-REQ04-002, TC-REQ04-003 | E5: Análisis de Valores Límite; Partición de Equivalencia | F5: Clientes | G5: Walter Rosales | H5: =COUNTIF(Log_Ejecucion!$B$2:$B$47,A5) | I5: =COUNTIFS(Log_Ejecucion!$B$2:$B$47,A5,Log_Ejecucion!$J$2:$J$47,"Pass") | J5: =COUNTIFS(Log_Ejecucion!$B$2:$B$47,A5,Log_Ejecucion!$J$2:$J$47,"Fail") | K5: =COUNTIFS(Log_Ejecucion!$B$2:$B$47,A5,Log_Ejecucion!$J$2:$J$47,"Blocked") | L5: =COUNTIFS(Log_Ejecucion!$B$2:$B$47,A5,Log_Ejecucion!$J$2:$J$47,"Pendiente") | M5: =IF(L5=H5,"Pendiente",IF(J5>0,"Con fallos",IF(I5=H5,"Aprobado","Parcial")))
A6: REQ-05 | B6: Alta | C6: R-07 | D6: TC-REQ05-001, TC-REQ05-002 | E6: Transición de Estados | F6: Clientes | G6: Walter Rosales | H6: =COUNTIF(Log_Ejecucion!$B$2:$B$47,A6) | I6: =COUNTIFS(Log_Ejecucion!$B$2:$B$47,A6,Log_Ejecucion!$J$2:$J$47,"Pass") | J6: =COUNTIFS(Log_Ejecucion!$B$2:$B$47,A6,Log_Ejecucion!$J$2:$J$47,"Fail") | K6: =COUNTIFS(Log_Ejecucion!$B$2:$B$47,A6,Log_Ejecucion!$J$2:$J$47,"Blocked") | L6: =COUNTIFS(Log_Ejecucion!$B$2:$B$47,A6,Log_Ejecucion!$J$2:$J$47,"Pendiente") | M6: =IF(L6=H6,"Pendiente",IF(J6>0,"Con fallos",IF(I6=H6,"Aprobado","Parcial")))
A7: REQ-06 | B7: Crítica | C7: R-07 | D7: TC-REQ06-001, TC-REQ06-002 | E7: Tabla de Decisión | F7: Cuentas | G7: Walter Rosales | H7: =COUNTIF(Log_Ejecucion!$B$2:$B$47,A7) | I7: =COUNTIFS(Log_Ejecucion!$B$2:$B$47,A7,Log_Ejecucion!$J$2:$J$47,"Pass") | J7: =COUNTIFS(Log_Ejecucion!$B$2:$B$47,A7,Log_Ejecucion!$J$2:$J$47,"Fail") | K7: =COUNTIFS(Log_Ejecucion!$B$2:$B$47,A7,Log_Ejecucion!$J$2:$J$47,"Blocked") | L7: =COUNTIFS(Log_Ejecucion!$B$2:$B$47,A7,Log_Ejecucion!$J$2:$J$47,"Pendiente") | M7: =IF(L7=H7,"Pendiente",IF(J7>0,"Con fallos",IF(I7=H7,"Aprobado","Parcial")))
A8: REQ-07 | B8: Alta | C8: R-03 | D8: TC-REQ07-001, TC-REQ07-002, TC-REQ07-003 | E8: Análisis de Valores Límite; Transición de Estados | F8: Cuentas | G8: Walter Rosales | H8: =COUNTIF(Log_Ejecucion!$B$2:$B$47,A8) | I8: =COUNTIFS(Log_Ejecucion!$B$2:$B$47,A8,Log_Ejecucion!$J$2:$J$47,"Pass") | J8: =COUNTIFS(Log_Ejecucion!$B$2:$B$47,A8,Log_Ejecucion!$J$2:$J$47,"Fail") | K8: =COUNTIFS(Log_Ejecucion!$B$2:$B$47,A8,Log_Ejecucion!$J$2:$J$47,"Blocked") | L8: =COUNTIFS(Log_Ejecucion!$B$2:$B$47,A8,Log_Ejecucion!$J$2:$J$47,"Pendiente") | M8: =IF(L8=H8,"Pendiente",IF(J8>0,"Con fallos",IF(I8=H8,"Aprobado","Parcial")))
A9: REQ-08 | B9: Crítica | C9: R-08 | D9: TC-REQ08-001, TC-REQ08-002, TC-REQ08-003 | E9: Análisis de Valores Límite; Partición de Equivalencia; Tabla de Decisión | F9: Caja | G9: Sergio Och | H9: =COUNTIF(Log_Ejecucion!$B$2:$B$47,A9) | I9: =COUNTIFS(Log_Ejecucion!$B$2:$B$47,A9,Log_Ejecucion!$J$2:$J$47,"Pass") | J9: =COUNTIFS(Log_Ejecucion!$B$2:$B$47,A9,Log_Ejecucion!$J$2:$J$47,"Fail") | K9: =COUNTIFS(Log_Ejecucion!$B$2:$B$47,A9,Log_Ejecucion!$J$2:$J$47,"Blocked") | L9: =COUNTIFS(Log_Ejecucion!$B$2:$B$47,A9,Log_Ejecucion!$J$2:$J$47,"Pendiente") | M9: =IF(L9=H9,"Pendiente",IF(J9>0,"Con fallos",IF(I9=H9,"Aprobado","Parcial")))
A10: REQ-09 | B10: Crítica | C10: R-03 | D10: TC-REQ09-001, TC-REQ09-002, TC-REQ09-003 | E10: Análisis de Valores Límite; Partición de Equivalencia; Tabla de Decisión | F10: Transacciones | G10: Sergio Och | H10: =COUNTIF(Log_Ejecucion!$B$2:$B$47,A10) | I10: =COUNTIFS(Log_Ejecucion!$B$2:$B$47,A10,Log_Ejecucion!$J$2:$J$47,"Pass") | J10: =COUNTIFS(Log_Ejecucion!$B$2:$B$47,A10,Log_Ejecucion!$J$2:$J$47,"Fail") | K10: =COUNTIFS(Log_Ejecucion!$B$2:$B$47,A10,Log_Ejecucion!$J$2:$J$47,"Blocked") | L10: =COUNTIFS(Log_Ejecucion!$B$2:$B$47,A10,Log_Ejecucion!$J$2:$J$47,"Pendiente") | M10: =IF(L10=H10,"Pendiente",IF(J10>0,"Con fallos",IF(I10=H10,"Aprobado","Parcial")))
A11: REQ-10 | B11: Crítica | C11: R-03 / R-05 | D11: TC-REQ10-001, TC-REQ10-002, TC-REQ10-003 | E11: Análisis de Valores Límite; Partición de Equivalencia | F11: Transacciones | G11: Sergio Och | H11: =COUNTIF(Log_Ejecucion!$B$2:$B$47,A11) | I11: =COUNTIFS(Log_Ejecucion!$B$2:$B$47,A11,Log_Ejecucion!$J$2:$J$47,"Pass") | J11: =COUNTIFS(Log_Ejecucion!$B$2:$B$47,A11,Log_Ejecucion!$J$2:$J$47,"Fail") | K11: =COUNTIFS(Log_Ejecucion!$B$2:$B$47,A11,Log_Ejecucion!$J$2:$J$47,"Blocked") | L11: =COUNTIFS(Log_Ejecucion!$B$2:$B$47,A11,Log_Ejecucion!$J$2:$J$47,"Pendiente") | M11: =IF(L11=H11,"Pendiente",IF(J11>0,"Con fallos",IF(I11=H11,"Aprobado","Parcial")))
A12: REQ-11 | B12: Crítica | C12: R-04 / R-05 | D12: TC-REQ11-001, TC-REQ11-002, TC-REQ11-003 | E12: Partición de Equivalencia; Tabla de Decisión | F12: Transacciones | G12: Sergio Och | H12: =COUNTIF(Log_Ejecucion!$B$2:$B$47,A12) | I12: =COUNTIFS(Log_Ejecucion!$B$2:$B$47,A12,Log_Ejecucion!$J$2:$J$47,"Pass") | J12: =COUNTIFS(Log_Ejecucion!$B$2:$B$47,A12,Log_Ejecucion!$J$2:$J$47,"Fail") | K12: =COUNTIFS(Log_Ejecucion!$B$2:$B$47,A12,Log_Ejecucion!$J$2:$J$47,"Blocked") | L12: =COUNTIFS(Log_Ejecucion!$B$2:$B$47,A12,Log_Ejecucion!$J$2:$J$47,"Pendiente") | M12: =IF(L12=H12,"Pendiente",IF(J12>0,"Con fallos",IF(I12=H12,"Aprobado","Parcial")))
A13: REQ-12 | B13: Crítica | C13: R-06 / R-05 | D13: TC-REQ12-001, TC-REQ12-002, TC-REQ12-003 | E13: Análisis de Valores Límite; Pairwise; Partición de Equivalencia | F13: Portal del cliente | G13: Walter Rosales | H13: =COUNTIF(Log_Ejecucion!$B$2:$B$47,A13) | I13: =COUNTIFS(Log_Ejecucion!$B$2:$B$47,A13,Log_Ejecucion!$J$2:$J$47,"Pass") | J13: =COUNTIFS(Log_Ejecucion!$B$2:$B$47,A13,Log_Ejecucion!$J$2:$J$47,"Fail") | K13: =COUNTIFS(Log_Ejecucion!$B$2:$B$47,A13,Log_Ejecucion!$J$2:$J$47,"Blocked") | L13: =COUNTIFS(Log_Ejecucion!$B$2:$B$47,A13,Log_Ejecucion!$J$2:$J$47,"Pendiente") | M13: =IF(L13=H13,"Pendiente",IF(J13>0,"Con fallos",IF(I13=H13,"Aprobado","Parcial")))
... A19: REQ-18 | B19: Alta | C19: R-07 / R-12 | D19: TC-REQ18-001, TC-REQ18-002 | E19: Tabla de Decisión | F19: Dependencias de datos | G19: Sergio Och | H19: =COUNTIF(Log_Ejecucion!$B$2:$B$47,A19) | I19: =COUNTIFS(Log_Ejecucion!$B$2:$B$47,A19,Log_Ejecucion!$J$2:$J$47,"Pass") | J19: =COUNTIFS(Log_Ejecucion!$B$2:$B$47,A19,Log_Ejecucion!$J$2:$J$47,"Fail") | K19: =COUNTIFS(Log_Ejecucion!$B$2:$B$47,A19,Log_Ejecucion!$J$2:$J$47,"Blocked") | L19: =COUNTIFS(Log_Ejecucion!$B$2:$B$47,A19,Log_Ejecucion!$J$2:$J$47,"Pendiente") | M19: =IF(L19=H19,"Pendiente",IF(J19>0,"Con fallos",IF(I19=H19,"Aprobado","Parcial")))

Sheet Log_Ejecucion
A1: ID_Caso | B1: ID_REQ | C1: Nombre_del_Caso | D1: Modulo | E1: P1 | F1: Especialista_QA_Ejecutor | G1: Fecha_Ejecucion | H1: Resultado_Esperado | I1: Resultado_Obtenido | J1: Estado_Ejecucion | K1: ID_Defecto_Asociado | L1: Evidencia | M1: Categoria_Criterio
A2: TC-REQ01-001 | B2: REQ-01 | C2: Login válido con usuario activo | D2: Seguridad y sesiones | E2: Sí | F2: Anderson Ariana | G2: 46317 | H2: HTTP 200. Devuelve token, refreshToken, roles y permisos; registra evento LOGIN exitoso y reinicia intentos fallidos. | I2: Ciclo 2 (22/10/2026, build corregida): 1 peticiones, 2 aserciones sin fallo; HTTP 200. Mismo comportamiento que en el ciclo 1: HTTP 200: token, refreshToken, rol ADMINISTRADOR, roles y permisos en la respuesta; ultimoLogin actualizado. | J2: Pass | K2: N/A | L2: Re_Prueba_Cierre_E3/04_Regresion_Completa/Anderson/TC-REQ01-001.json; Re_Prueba_Cierre_E3/05_Verificaciones_SQL/TC-REQ01-001.txt · Ciclo 1: Resultados_Newman/Anderson/TC-REQ01-001.json | M2: —
A3: TC-REQ01-002 | B3: REQ-01 | C3: Bloqueo en frontera de intentos fallidos | D3: Seguridad y sesiones | E3: Sí | F3: Anderson Ariana | G3: 46317 | H3: Intentos 1-4: HTTP 401 e indica 'Intento X de 5'. Intento 5: HTTP 401 y usuario queda bloqueado; sesiones se revocan. Intento posterior: HTTP 423 mientras el bloqueo siga vigente. | I3: Ciclo 2 (22/10/2026, build corregida): 6 peticiones, 10 aserciones sin fallo; HTTP 401, 401, 401, 401, 401, 423. Mismo comportamiento que en el ciclo 1: Intentos 1-4: HTTP 401 'Credenciales incorrectas. Intento X de 5.'; intento 5: HTTP 401 y qa_bloqueo queda bloqueado=true, intentos=5, bloqueado_hasta +30 min; 6.º intento con clave correcta: HTTP 423 'El usuario se encuentra bloqueado...'. Eventos LOGIN_FALLIDO ×5 y USUARIO_BLOQUEADO en BD. | J3: Pass | K3: N/A | L3: Re_Prueba_Cierre_E3/04_Regresion_Completa/Anderson/TC-REQ01-002.json; Re_Prueba_Cierre_E3/05_Verificaciones_SQL/TC-REQ01-002.txt · Ciclo 1: Resultados_Newman/Anderson/TC-REQ01-002.json; Logs_Consola_Servidor/Verificaciones_SQL/TC-REQ01-002.txt | M3: —
A4: TC-REQ01-003 | B4: REQ-01 | C4: Rechazo de usuario inactivo o bloqueado | D4: Seguridad y sesiones | E4: Sí | F4: Anderson Ariana | G4: 46317 | H4: Inactivo: HTTP 403, 'El usuario se encuentra inactivo...'. Bloqueado: HTTP 423, 'El usuario se encuentra bloqueado...'. No se entrega token. | I4: Ciclo 2 (22/10/2026, build corregida): 2 peticiones, 6 aserciones sin fallo; HTTP 403, 423. Mismo comportamiento que en el ciclo 1: qa_inactivo: HTTP 403 'El usuario se encuentra inactivo. Por favor comuniquese con soporte.'; qa_bloqueado: HTTP 423 'El usuario se encuentra bloqueado...'. Sin token en ninguna respuesta. | J4: Pass | K4: N/A | L4: Re_Prueba_Cierre_E3/04_Regresion_Completa/Anderson/TC-REQ01-003.json; Re_Prueba_Cierre_E3/05_Verificaciones_SQL/TC-REQ01-003.txt · Ciclo 1: Resultados_Newman/Anderson/TC-REQ01-003.json | M4: —
A5: TC-REQ02-001 | B5: REQ-02 | C5: Rotación de refresh token | D5: Seguridad y sesiones | E5: Sí | F5: Anderson Ariana | G5: 46317 | H5: Primera llamada HTTP 200 y entrega nuevos tokens. El refresh anterior queda rotado; su reutilización debe ser rechazada como inválida/expirada (HTTP 401). | I5: Ciclo 2 (22/10/2026, build corregida): 3 peticiones, 4 aserciones sin fallo; HTTP 200, 200, 401. Mismo comportamiento que en el ciclo 1: Refresh con refresh_v1: HTTP 200 con tokens nuevos y refresh distinto; reutilizar refresh_v1: HTTP 401 'Refresh token invalido o expirado.' | J5: Pass | K5: N/A | L5: Re_Prueba_Cierre_E3/04_Regresion_Completa/Anderson/TC-REQ02-001.json; Re_Prueba_Cierre_E3/05_Verificaciones_SQL/TC-REQ02-001.txt · Ciclo 1: Resultados_Newman/Anderson/TC-REQ02-001.json; Logs_Consola_Servidor/Verificaciones_SQL/TC-REQ02.txt | M5: —
A6: TC-REQ02-002 | B6: REQ-02 | C6: Logout revoca la sesión activa | D6: Seguridad y sesiones | E6: Sí | F6: Anderson Ariana | G6: 46317 | H6: Logout exitoso. La sesión queda revocada; solicitudes posteriores con esa sesión fallan autenticación y el refresh no genera una nueva sesión. | I6: Ciclo 2 (22/10/2026, build corregida): 4 peticiones, 4 aserciones sin fallo; HTTP 200, 200, 401, 401. Mismo comportamiento que en el ciclo 1: Logout HTTP 200; /api/auth/me con el mismo access token: HTTP 401; refresh de la sesión revocada: HTTP 401. En BD la sesión queda estado=false con fecha_cierre. | J6: Pass | K6: N/A | L6: Re_Prueba_Cierre_E3/04_Regresion_Completa/Anderson/TC-REQ02-002.json; Re_Prueba_Cierre_E3/05_Verificaciones_SQL/TC-REQ02-002.txt · Ciclo 1: Resultados_Newman/Anderson/TC-REQ02-002.json; Logs_Consola_Servidor/Verificaciones_SQL/TC-REQ02.txt | M6: —
A7: TC-REQ03-001 | B7: REQ-03 | C7: Acceso permitido con permiso requerido | D7: Seguridad y sesiones | E7: Sí | F7: Anderson Ariana | G7: 46317 | H7: HTTP 200 y acceso únicamente al recurso autorizado. | I7: Ciclo 2 (22/10/2026, build corregida): 1 peticiones, 1 aserciones sin fallo; HTTP 200. Mismo comportamiento que en el ciclo 1: GET /api/clientes con qa_admin: HTTP 200 con el listado de clientes. | J7: Pass | K7: N/A | L7: Re_Prueba_Cierre_E3/04_Regresion_Completa/Anderson/TC-REQ03-001.json; Re_Prueba_Cierre_E3/05_Verificaciones_SQL/TC-REQ03-001.txt · Ciclo 1: Resultados_Newman/Anderson/TC-REQ03-001.json | M7: Autorización
A8: TC-REQ03-002 | B8: REQ-03 | C8: Denegación por rol/permiso insuficiente | D8: Seguridad y sesiones | E8: Sí | F8: Anderson Ariana | G8: 46317 | H8: HTTP 403/denegación en cada combinación no autorizada; ninguna operación negada modifica datos. | I8: Ciclo 2 (22/10/2026, build corregida): 5 peticiones, 6 aserciones sin fallo; HTTP 403, 403, 403, 401, 401. Incluye la fila P7-ACH automatizada: GET /api/ach/bancos sin token → HTTP 401 (ciclo 1: HTTP 200, BUG-NEX-01). P2 y el POST con token CLIENTE → 403; P4 → 403; P7 /api/clientes → 401. | J8: Pass | K8: BUG-NEX-01 (cerrado 22/10/2026) | L8: Re_Prueba_Cierre_E3/04_Regresion_Completa/Anderson/TC-REQ03-002.json; Re_Prueba_Cierre_E3/05_Verificaciones_SQL/TC-REQ03-002.txt · Ciclo 1: Resultados_Newman/Anderson/TC-REQ03-002.json; Capturas_Bugs/Evidencia_BUG01_Anderson.png | M8: Autorización
A9: TC-REQ04-001 | B9: REQ-04 | C9: Registro válido en frontera exacta de 18 años | D9: Clientes | E9: No | F9: Walter Rosales | G9: 46317 | H9: HTTP 201. Cliente creado y estado inicial EN_REVISION; no se rechaza por edad al cumplir exactamente 18. | I9: Ciclo 2 (22/10/2026, build corregida): 3 peticiones, 4 aserciones sin fallo; HTTP 201, 200, 400. Mismo comportamiento que en el ciclo 1: Diego (nac. 2008-10-20, 18 años exactos a la fecha del servidor 2026-10-20 UTC): HTTP 201 'Cliente registrado en revision', GET muestra EN_REVISION. Variante menor por 1 día (2008-10-21): HTTP 400 'El cliente tiene 17 anos. Minimo: 18' y no se crea. | J9: Pass | K9: N/A | L9: Re_Prueba_Cierre_E3/04_Regresion_Completa/Walter/TC-REQ04-001.json; Re_Prueba_Cierre_E3/05_Verificaciones_SQL/TC-REQ04-001.txt · Ciclo 1: Resultados_Newman/Walter/TC-REQ04-001.json; Logs_Consola_Servidor/Verificaciones_SQL/REQ-04_Clientes.txt | M9: —
A10: TC-REQ04-002 | B10: REQ-04 | C10: Fronteras y duplicidad de DPI | D10: Clientes | E10: No | F10: Walter Rosales | G10: 46317 | H10: 12/14 dígitos: HTTP 400 'DPI invalido. Debe tener 13 digitos'. 13 nuevo: aceptado si resto válido. Duplicado: HTTP 409 'Ya existe cliente con ese DPI'. | I10: Ciclo 2 (22/10/2026, build corregida): 4 peticiones, 7 aserciones sin fallo; HTTP 400, 201, 400, 409. Mismo comportamiento que en el ciclo 1: DPI 12 y 14 dígitos: HTTP 400 'DPI invalido. Debe tener 13 digitos'; DPI 13 nuevo: HTTP 201; DPI duplicado 2999999990101: HTTP 409 'Ya existe cliente con ese DPI'. En BD solo se creó 2999999990198. | J10: Pass | K10: N/A | L10: Re_Prueba_Cierre_E3/04_Regresion_Completa/Walter/TC-REQ04-002.json; Re_Prueba_Cierre_E3/05_Verificaciones_SQL/TC-REQ04-002.txt · Ciclo 1: Resultados_Newman/Walter/TC-REQ04-002.json; Logs_Consola_Servidor/Verificaciones_SQL/REQ-04_Clientes.txt | M10: —
A11: TC-REQ04-003 | B11: REQ-04 | C11: Validación de correo y teléfono | D11: Clientes | E11: No | F11: Walter Rosales | G11: 46317 | H11: Correo inválido: HTTP 400 'Email con formato invalido'. Teléfono inválido: HTTP 400 'Telefono invalido. Debe tener 8 digitos'. | I11: Ciclo 2 (22/10/2026, build corregida): 3 peticiones, 6 aserciones sin fallo; HTTP 400, 400, 400. Mismo comportamiento que en el ciclo 1: Correo sin @: HTTP 400 'Email con formato invalido'; teléfono 7 y 9 dígitos: HTTP 400 'Telefono invalido. Debe tener 8 digitos'. No se creó el DPI 2999999990196. | J11: Pass | K11: N/A | L11: Re_Prueba_Cierre_E3/04_Regresion_Completa/Walter/TC-REQ04-003.json; Re_Prueba_Cierre_E3/05_Verificaciones_SQL/TC-REQ04-003.txt · Ciclo 1: Resultados_Newman/Walter/TC-REQ04-003.json; Logs_Consola_Servidor/Verificaciones_SQL/REQ-04_Clientes.txt | M11: —
A12: TC-REQ05-001 | B12: REQ-05 | C12: Estado inicial del cliente | D12: Clientes | E12: No | F12: Walter Rosales | G12: 46317 | H12: Estado devuelto EN_REVISION; no ACTIVO automáticamente. | I12: Ciclo 2 (22/10/2026, build corregida): 2 peticiones, 3 aserciones sin fallo; HTTP 201, 200. Mismo comportamiento que en el ciclo 1: Registro de Elena: HTTP 201; GET devuelve estado EN_REVISION (no ACTIVO). Auditoría CRM REGISTRO_CLIENTE. | J12: Pass | K12: N/A | L12: Re_Prueba_Cierre_E3/04_Regresion_Completa/Walter/TC-REQ05-001.json; Re_Prueba_Cierre_E3/05_Verificaciones_SQL/TC-REQ05-001.txt · Ciclo 1: Resultados_Newman/Walter/TC-REQ05-001.json | M12: —
A13: TC-REQ05-002 | B13: REQ-05 | C13: EN_REVISION no abre cuenta; ACTIVO sí puede continuar | D13: Clientes | E13: No | F13: Walter Rosales | G13: 46317 | H13: Antes de aprobar: HTTP 422 indicando cliente no activo. Tras pasar a ACTIVO, la validación de estado deja de bloquear la apertura y el flujo continúa. | I13: Ciclo 2 (22/10/2026, build corregida): 4 peticiones, 4 aserciones sin fallo; HTTP 200, 422, 200, 201. Mismo comportamiento que en el ciclo 1: Apertura con Carla EN_REVISION: HTTP 422 'El cliente no esta activo. Estado: EN_REVISION' (0 cuentas); PATCH a ACTIVO: HTTP 200; nueva apertura: HTTP 201 AH261020854073 ACTIVA, saldo 0, mínimo Q100. | J13: Pass | K13: N/A | L13: Re_Prueba_Cierre_E3/04_Regresion_Completa/Walter/TC-REQ05-002.json; Re_Prueba_Cierre_E3/05_Verificaciones_SQL/TC-REQ05-002.txt · Ciclo 1: Resultados_Newman/Walter/TC-REQ05-002.json; Logs_Consola_Servidor/Verificaciones_SQL/TC-REQ05-002.txt | M13: —
... A47: TC-REQ18-002 | B47: REQ-18 | C47: Dependencias de catálogo/plan contable determinan readiness | D47: Dependencias de datos | E47: No | F47: Sergio Och | G47: 46317 | H47: Con seeds válidos el flujo continúa. Si falta cuenta contable requerida, depósito/retiro falla 422 con mensaje 'No existe cuenta contable activa con codigo ...'. Se clasifica como fallo de ambiente, no como defecto del caso funcional. | I47: Ciclo 2 (22/10/2026, build corregida): 3 peticiones, 4 aserciones sin fallo; HTTP 422, 200, 422. Mismo comportamiento que en el ciclo 1: Plan completo: depósito Q10 HTTP 200 con asientos DB 1101 / CR 2101. Con 1101 inactiva: HTTP 422 'No existe cuenta contable activa con codigo 1101 en contabilidad.plan_cuentas.' sin movimiento; 1101 restaurada. | J47: Pass | K47: N/A | L47: Re_Prueba_Cierre_E3/04_Regresion_Completa/Sergio/TC-REQ18-002_parte1_plan_completo.json; Re_Prueba_Cierre_E3/04_Regresion_Completa/Sergio/TC-REQ18-002_parte2_1101_inactiva.json; Re_Prueba_Cierre_E3/05_Verificaciones_SQL/TC-REQ18-002.txt · Ciclo 1: Resultados_Newman/Sergio/TC-REQ18-002_parte1_plan_completo.json, _parte2_1101_inactiva.json; Logs_Consola_Servidor/Verificaciones_SQL/TC-REQ18-002.txt | M47: —

Sheet Log_Ciclo1_19-10
A1: ID_Caso | B1: ID_REQ | C1: Nombre_del_Caso | D1: Modulo | E1: P1 | F1: Especialista_QA_Ejecutor | G1: Fecha_Ejecucion | H1: Resultado_Esperado | I1: Resultado_Obtenido | J1: Estado_Ejecucion | K1: ID_Defecto_Asociado | L1: Evidencia | M1: Categoria_Criterio
A2: TC-REQ01-001 | B2: REQ-01 | C2: Login válido con usuario activo | D2: Seguridad y sesiones | E2: Sí | F2: Anderson Ariana | G2: 46314 | H2: HTTP 200. Devuelve token, refreshToken, roles y permisos; registra evento LOGIN exitoso y reinicia intentos fallidos. | I2: HTTP 200: token, refreshToken, rol ADMINISTRADOR, roles y permisos en la respuesta; ultimoLogin actualizado. | J2: Pass | K2: N/A | L2: Resultados_Newman/Anderson/TC-REQ01-001.json | M2: —
A3: TC-REQ01-002 | B3: REQ-01 | C3: Bloqueo en frontera de intentos fallidos | D3: Seguridad y sesiones | E3: Sí | F3: Anderson Ariana | G3: 46314 | H3: Intentos 1-4: HTTP 401 e indica 'Intento X de 5'. Intento 5: HTTP 401 y usuario queda bloqueado; sesiones se revocan. Intento posterior: HTTP 423 mientras el bloqueo siga vigente. | I3: Intentos 1-4: HTTP 401 'Credenciales incorrectas. Intento X de 5.'; intento 5: HTTP 401 y qa_bloqueo queda bloqueado=true, intentos=5, bloqueado_hasta +30 min; 6.º intento con clave correcta: HTTP 423 'El usuario se encuentra bloqueado...'. Eventos LOGIN_FALLIDO ×5 y USUARIO_BLOQUEADO en BD. | J3: Pass | K3: N/A | L3: Resultados_Newman/Anderson/TC-REQ01-002.json; Logs_Consola_Servidor/Verificaciones_SQL/TC-REQ01-002.txt | M3: —
A4: TC-REQ01-003 | B4: REQ-01 | C4: Rechazo de usuario inactivo o bloqueado | D4: Seguridad y sesiones | E4: Sí | F4: Anderson Ariana | G4: 46314 | H4: Inactivo: HTTP 403, 'El usuario se encuentra inactivo...'. Bloqueado: HTTP 423, 'El usuario se encuentra bloqueado...'. No se entrega token. | I4: qa_inactivo: HTTP 403 'El usuario se encuentra inactivo. Por favor comuniquese con soporte.'; qa_bloqueado: HTTP 423 'El usuario se encuentra bloqueado...'. Sin token en ninguna respuesta. | J4: Pass | K4: N/A | L4: Resultados_Newman/Anderson/TC-REQ01-003.json | M4: —
A5: TC-REQ02-001 | B5: REQ-02 | C5: Rotación de refresh token | D5: Seguridad y sesiones | E5: Sí | F5: Anderson Ariana | G5: 46314 | H5: Primera llamada HTTP 200 y entrega nuevos tokens. El refresh anterior queda rotado; su reutilización debe ser rechazada como inválida/expirada (HTTP 401). | I5: Refresh con refresh_v1: HTTP 200 con tokens nuevos y refresh distinto; reutilizar refresh_v1: HTTP 401 'Refresh token invalido o expirado.' | J5: Pass | K5: N/A | L5: Resultados_Newman/Anderson/TC-REQ02-001.json; Logs_Consola_Servidor/Verificaciones_SQL/TC-REQ02.txt | M5: —
A6: TC-REQ02-002 | B6: REQ-02 | C6: Logout revoca la sesión activa | D6: Seguridad y sesiones | E6: Sí | F6: Anderson Ariana | G6: 46314 | H6: Logout exitoso. La sesión queda revocada; solicitudes posteriores con esa sesión fallan autenticación y el refresh no genera una nueva sesión. | I6: Logout HTTP 200; /api/auth/me con el mismo access token: HTTP 401; refresh de la sesión revocada: HTTP 401. En BD la sesión queda estado=false con fecha_cierre. | J6: Pass | K6: N/A | L6: Resultados_Newman/Anderson/TC-REQ02-002.json; Logs_Consola_Servidor/Verificaciones_SQL/TC-REQ02.txt | M6: —
A7: TC-REQ03-001 | B7: REQ-03 | C7: Acceso permitido con permiso requerido | D7: Seguridad y sesiones | E7: Sí | F7: Anderson Ariana | G7: 46314 | H7: HTTP 200 y acceso únicamente al recurso autorizado. | I7: GET /api/clientes con qa_admin: HTTP 200 con el listado de clientes. | J7: Pass | K7: N/A | L7: Resultados_Newman/Anderson/TC-REQ03-001.json | M7: Autorización
A8: TC-REQ03-002 | B8: REQ-03 | C8: Denegación por rol/permiso insuficiente | D8: Seguridad y sesiones | E8: Sí | F8: Anderson Ariana | G8: 46314 | H8: HTTP 403/denegación en cada combinación no autorizada; ninguna operación negada modifica datos. | I8: P2 CLIENTE→/api/clientes: 403; P4 JWT BANCO_EXTERNO→InternalAPI: 403; POST cliente con token CLIENTE: 403 (DPI 2999999990194 no se crea); P7 sin token→/api/clientes: 401. Fila adicional P7 sin token→GET /api/ach/bancos: HTTP 200 con la configuración ACH (también /activos; PATCH anónimo llega al servicio: 404). Combinación no autorizada no denegada. | J8: Fail | K8: BUG-NEX-01 | L8: Resultados_Newman/Anderson/TC-REQ03-002.json; Capturas_Bugs/Evidencia_BUG01_Anderson.png | M8: Autorización
A9: TC-REQ04-001 | B9: REQ-04 | C9: Registro válido en frontera exacta de 18 años | D9: Clientes | E9: No | F9: Walter Rosales | G9: 46314 | H9: HTTP 201. Cliente creado y estado inicial EN_REVISION; no se rechaza por edad al cumplir exactamente 18. | I9: Diego (nac. 2008-10-20, 18 años exactos a la fecha del servidor 2026-10-20 UTC): HTTP 201 'Cliente registrado en revision', GET muestra EN_REVISION. Variante menor por 1 día (2008-10-21): HTTP 400 'El cliente tiene 17 anos. Minimo: 18' y no se crea. | J9: Pass | K9: N/A | L9: Resultados_Newman/Walter/TC-REQ04-001.json; Logs_Consola_Servidor/Verificaciones_SQL/REQ-04_Clientes.txt | M9: —
A10: TC-REQ04-002 | B10: REQ-04 | C10: Fronteras y duplicidad de DPI | D10: Clientes | E10: No | F10: Walter Rosales | G10: 46314 | H10: 12/14 dígitos: HTTP 400 'DPI invalido. Debe tener 13 digitos'. 13 nuevo: aceptado si resto válido. Duplicado: HTTP 409 'Ya existe cliente con ese DPI'. | I10: DPI 12 y 14 dígitos: HTTP 400 'DPI invalido. Debe tener 13 digitos'; DPI 13 nuevo: HTTP 201; DPI duplicado 2999999990101: HTTP 409 'Ya existe cliente con ese DPI'. En BD solo se creó 2999999990198. | J10: Pass | K10: N/A | L10: Resultados_Newman/Walter/TC-REQ04-002.json; Logs_Consola_Servidor/Verificaciones_SQL/REQ-04_Clientes.txt | M10: —
A11: TC-REQ04-003 | B11: REQ-04 | C11: Validación de correo y teléfono | D11: Clientes | E11: No | F11: Walter Rosales | G11: 46314 | H11: Correo inválido: HTTP 400 'Email con formato invalido'. Teléfono inválido: HTTP 400 'Telefono invalido. Debe tener 8 digitos'. | I11: Correo sin @: HTTP 400 'Email con formato invalido'; teléfono 7 y 9 dígitos: HTTP 400 'Telefono invalido. Debe tener 8 digitos'. No se creó el DPI 2999999990196. | J11: Pass | K11: N/A | L11: Resultados_Newman/Walter/TC-REQ04-003.json; Logs_Consola_Servidor/Verificaciones_SQL/REQ-04_Clientes.txt | M11: —
A12: TC-REQ05-001 | B12: REQ-05 | C12: Estado inicial del cliente | D12: Clientes | E12: No | F12: Walter Rosales | G12: 46314 | H12: Estado devuelto EN_REVISION; no ACTIVO automáticamente. | I12: Registro de Elena: HTTP 201; GET devuelve estado EN_REVISION (no ACTIVO). Auditoría CRM REGISTRO_CLIENTE. | J12: Pass | K12: N/A | L12: Resultados_Newman/Walter/TC-REQ05-001.json | M12: —
A13: TC-REQ05-002 | B13: REQ-05 | C13: EN_REVISION no abre cuenta; ACTIVO sí puede continuar | D13: Clientes | E13: No | F13: Walter Rosales | G13: 46314 | H13: Antes de aprobar: HTTP 422 indicando cliente no activo. Tras pasar a ACTIVO, la validación de estado deja de bloquear la apertura y el flujo continúa. | I13: Apertura con Carla EN_REVISION: HTTP 422 'El cliente no esta activo. Estado: EN_REVISION' (0 cuentas); PATCH a ACTIVO: HTTP 200; nueva apertura: HTTP 201 AH261020854073 ACTIVA, saldo 0, mínimo Q100. | J13: Pass | K13: N/A | L13: Resultados_Newman/Walter/TC-REQ05-002.json; Logs_Consola_Servidor/Verificaciones_SQL/TC-REQ05-002.txt | M13: —
... A47: TC-REQ18-002 | B47: REQ-18 | C47: Dependencias de catálogo/plan contable determinan readiness | D47: Dependencias de datos | E47: No | F47: Sergio Och | G47: 46314 | H47: Con seeds válidos el flujo continúa. Si falta cuenta contable requerida, depósito/retiro falla 422 con mensaje 'No existe cuenta contable activa con codigo ...'. Se clasifica como fallo de ambiente, no como defecto del caso funcional. | I47: Plan completo: depósito Q10 HTTP 200 con asientos DB 1101 / CR 2101. Con 1101 inactiva: HTTP 422 'No existe cuenta contable activa con codigo 1101 en contabilidad.plan_cuentas.' sin movimiento; 1101 restaurada. | J47: Pass | K47: N/A | L47: Resultados_Newman/Sergio/TC-REQ18-002_parte1_plan_completo.json, _parte2_1101_inactiva.json; Logs_Consola_Servidor/Verificaciones_SQL/TC-REQ18-002.txt | M47: —

Sheet Bug_Tracker
A1: ID_Bug | B1: ID_Caso | C1: Modulo | D1: Titulo_del_Defecto | E1: Especialista_QA_Reporta | F1: Desarrollador_Asignado | G1: Severidad | H1: Prioridad | I1: Estado_Bug | J1: Fecha_Deteccion | K1: Evidencia_Adjunta | L1: Origen | M1: Fecha_Correccion | N1: Correccion_Aplicada | O1: Fecha_Re_Prueba | P1: Resultado_Re_Prueba | Q1: Evidencia_Re_Prueba
A2: BUG-NEX-01 | B2: TC-REQ03-002 | C2: Seguridad y sesiones | D2: GET /api/ach/bancos devuelve la configuración ACH sin token (HTTP 200) | E2: Anderson Ariana | F2: Equipo de Desarrollo BancoERP (backend InternalAPI) | G2: Alta | H2: Alta | I2: Cerrado | J2: 06/10/2026 | K2: Capturas_Bugs/Evidencia_BUG01_Anderson.png (.txt); Logs_Consola_Servidor/BUG01_internal-api.log; Logs_Consola_Servidor/Readiness_Log.txt (OBS-01) | L2: Detectado por el script de readiness (observación OBS-01) en el entorno QA real; en la E3 se re-verificó como fila adicional P7 del Pairwise de TC-REQ03-002 (caso en Fail); TC-REQ13-002 solo lo observa fuera de su oráculo y queda en Pass. Confirmado en E3 el 19/10/2026: GET /api/ach/bancos y /activos sin token → HTTP 200; PATCH anónimo llega al servicio (404, no 401). Re-verificado tras la regresión P1: sigue abierto. | M2: 22/10/2026 | N2: [Authorize] en AchBancosController y [RequirePermission(ach.bancos.*)] en sus acciones administrativas (GET /activos solo exige sesión); [Authorize] en AchTransferenciasController; prueba unitaria InternalApiAuthorizationTests. Requiere 009_ach_seed.sql (en la secuencia de producción). | O2: 22/10/2026 | P2: Aprobada: 9 rutas sin token → 401; 5 roles sin permiso → 403; ADMIN/cajero/cliente → 200; Mongo sin cambios; TC-REQ03-002 6/6; unitarias 26/26 (16/26 sin corrección). | Q2: Re_Prueba_Cierre_E3/06_Capturas/Evidencia_Re_Prueba_BUG01_Luis.png; 03_Re_Prueba_Defectos/BUG-NEX-01; 02_Pruebas_Unitarias
A3: BUG-NEX-02 | B3: TC-REQ16-001 | C3: Auditoría y reportes | D3: GET /api/reportes/resumen no contabiliza las transferencias ACH entrantes aprobadas (achAprobadas=0, montoAch=0) | E3: Luis Contreras | F3: Equipo de Desarrollo BancoERP (backend InternalAPI – ReporteService) | G3: Alta | H3: Media | I3: Cerrado | J3: 19/10/2026 | K3: Capturas_Bugs/Evidencia_BUG02_Luis.png (.txt); Logs_Consola_Servidor/BUG02_internal-api.log; Resultados_Newman/Luis/TC-REQ16-001.json | L3: Ejecución E3 de TC-REQ16-001 sobre la BD aislada bancoerp_e2_qa_rep01 (fixture REP-01). | M3: 22/10/2026 | N3: ReporteService: achSql y la serie de 7 días suman ach.transferencias y ach.transferencias_entrantes (UNION ALL). Oráculo de TC-REQ16-001 reforzado a 11 totales. | O3: 22/10/2026 | P3: Aprobada: TC-REQ16-001 14/14 aserciones (achAprobadas 1, montoAch 25); control cruzado API = SQL en la BD principal (3 ACH, Q525). | Q3: Re_Prueba_Cierre_E3/06_Capturas/Evidencia_Re_Prueba_BUG02_Luis.png; 03_Re_Prueba_Defectos/BUG-NEX-02

Sheet Fichas_Defectos
A1: Campo | B1: Detalle
A2: ID Defecto | B2: BUG-NEX-01
A3: Título | B3: GET /api/ach/bancos devuelve la configuración ACH sin token (HTTP 200)
A4: Especialista QA Reportador | B4: Anderson Ariana
A5: Desarrollador asignado | B5: Equipo de Desarrollo BancoERP (backend InternalAPI)
A6: Fecha de detección | B6: 06/10/2026
A7: Severidad / Prioridad | B7: Alta / Alta
A8: Estado | B8: Cerrado — 22/10/2026 (re-prueba aprobada y regresión completa sin fallos)
A9: Ambiente de prueba | B9: QA local docker-compose.qa.yml · InternalAPI http://localhost:15141 · BD bancoerp_e2_qa · baseline 28f3faf
A10: Precondiciones | B10: Entorno QA levantado; existen bancos ACH configurados en MongoDB (5 bancos simulados E2_QA_*). Sin encabezado Authorization.
A11: Pasos para reproducir | B11: 1. Abrir Postman (o curl) sin token ni encabezado Authorization. 2. Enviar GET http://localhost:15141/api/ach/bancos. 3. Observar el código HTTP y el cuerpo de la respuesta.
A12: Resultado esperado | B12: HTTP 401: la configuración ACH requiere JWT; sin token no se devuelve ningún dato (regla de autorización REQ-03 y decisión de configuración ACH con permiso administrativo).
... A42: Evidencia de cierre | B42: Re_Prueba_Cierre_E3/06_Capturas/Evidencia_Re_Prueba_BUG02_Luis.png; 03_Re_Prueba_Defectos/BUG-NEX-02

Sheet Metricas_TSR
A1: Métrica | B1: Valor | C1: Fórmula / nota
A2: Casos planificados | B2: =COUNTA(Log_Ejecucion!$A$2:$A$47) | C2: Total de casos del repositorio E2
A3: Pass | B3: =COUNTIF(Log_Ejecucion!$J$2:$J$47,"Pass")
A4: Fail | B4: =COUNTIF(Log_Ejecucion!$J$2:$J$47,"Fail")
A5: Blocked | B5: =COUNTIF(Log_Ejecucion!$J$2:$J$47,"Blocked")
A6: Skipped | B6: =COUNTIF(Log_Ejecucion!$J$2:$J$47,"Skipped")
A7: Pendientes | B7: =COUNTIF(Log_Ejecucion!$J$2:$J$47,"Pendiente")
A8: Casos ejecutados | B8: =B3+B4 | C8: Pass + Fail
A9: Porcentaje de ejecución | B9: =IF(B2=0,0,B8/B2) | C9: Ejecutados / Planificados
A10: Tasa de éxito (Pass Rate) | B10: =IF(B8=0,0,B3/B8) | C10: Pass / Ejecutados
A11: Casos P1 planificados | B11: =COUNTIF(Log_Ejecucion!$E$2:$E$47,"Sí") | C11: Casos de REQ con prioridad Crítica en E1
A12: Casos P1 ejecutados | B12: =COUNTIFS(Log_Ejecucion!$E$2:$E$47,"Sí",Log_Ejecucion!$J$2:$J$47,"Pass")+COUNTIFS(Log_Ejecucion!$E$2:$E$47,"Sí",Log_Ejecucion!$J$2:$J$47,"Fail")
A13: Porcentaje P1 ejecutado | B13: =IF(B11=0,0,B12/B11)
A14: Defectos registrados | B14: =COUNTA(Bug_Tracker!$A$2:$A$41)
A15: Defectos Críticos abiertos | B15: =COUNTIFS(Bug_Tracker!$G$2:$G$41,"Crítica",Bug_Tracker!$I$2:$I$41,"<>Cerrado") | C15: Abierto = cualquier estado distinto de Cerrado
A16: Defectos Altos abiertos | B16: =COUNTIFS(Bug_Tracker!$G$2:$G$41,"Alta",Bug_Tracker!$I$2:$I$41,"<>Cerrado")
A17: Defectos Medios abiertos | B17: =COUNTIFS(Bug_Tracker!$G$2:$G$41,"Media",Bug_Tracker!$I$2:$I$41,"<>Cerrado")
A18: Defectos Bajos abiertos | B18: =COUNTIFS(Bug_Tracker!$G$2:$G$41,"Baja",Bug_Tracker!$I$2:$I$41,"<>Cerrado")
A19: Defectos cerrados | B19: =COUNTIF(Bug_Tracker!$I$2:$I$41,"Cerrado")
A20: Densidad global (defectos / caso) | B20: =IF(B2=0,0,B14/B2)
A22: Módulo | B22: Casos | C22: Defectos | D22: Densidad (defectos / caso) | E22: Pass | F22: Fail
A23: Seguridad y sesiones | B23: =COUNTIF(Log_Ejecucion!$D$2:$D$47,A23) | C23: =COUNTIF(Bug_Tracker!$C$2:$C$41,A23) | D23: =IF(B23=0,0,C23/B23) | E23: =COUNTIFS(Log_Ejecucion!$D$2:$D$47,A23,Log_Ejecucion!$J$2:$J$47,"Pass") | F23: =COUNTIFS(Log_Ejecucion!$D$2:$D$47,A23,Log_Ejecucion!$J$2:$J$47,"Fail")
A24: Clientes | B24: =COUNTIF(Log_Ejecucion!$D$2:$D$47,A24) | C24: =COUNTIF(Bug_Tracker!$C$2:$C$41,A24) | D24: =IF(B24=0,0,C24/B24) | E24: =COUNTIFS(Log_Ejecucion!$D$2:$D$47,A24,Log_Ejecucion!$J$2:$J$47,"Pass") | F24: =COUNTIFS(Log_Ejecucion!$D$2:$D$47,A24,Log_Ejecucion!$J$2:$J$47,"Fail")
A25: Cuentas | B25: =COUNTIF(Log_Ejecucion!$D$2:$D$47,A25) | C25: =COUNTIF(Bug_Tracker!$C$2:$C$41,A25) | D25: =IF(B25=0,0,C25/B25) | E25: =COUNTIFS(Log_Ejecucion!$D$2:$D$47,A25,Log_Ejecucion!$J$2:$J$47,"Pass") | F25: =COUNTIFS(Log_Ejecucion!$D$2:$D$47,A25,Log_Ejecucion!$J$2:$J$47,"Fail")
A26: Caja | B26: =COUNTIF(Log_Ejecucion!$D$2:$D$47,A26) | C26: =COUNTIF(Bug_Tracker!$C$2:$C$41,A26) | D26: =IF(B26=0,0,C26/B26) | E26: =COUNTIFS(Log_Ejecucion!$D$2:$D$47,A26,Log_Ejecucion!$J$2:$J$47,"Pass") | F26: =COUNTIFS(Log_Ejecucion!$D$2:$D$47,A26,Log_Ejecucion!$J$2:$J$47,"Fail")
A27: Transacciones | B27: =COUNTIF(Log_Ejecucion!$D$2:$D$47,A27) | C27: =COUNTIF(Bug_Tracker!$C$2:$C$41,A27) | D27: =IF(B27=0,0,C27/B27) | E27: =COUNTIFS(Log_Ejecucion!$D$2:$D$47,A27,Log_Ejecucion!$J$2:$J$47,"Pass") | F27: =COUNTIFS(Log_Ejecucion!$D$2:$D$47,A27,Log_Ejecucion!$J$2:$J$47,"Fail")
A28: Portal del cliente | B28: =COUNTIF(Log_Ejecucion!$D$2:$D$47,A28) | C28: =COUNTIF(Bug_Tracker!$C$2:$C$41,A28) | D28: =IF(B28=0,0,C28/B28) | E28: =COUNTIFS(Log_Ejecucion!$D$2:$D$47,A28,Log_Ejecucion!$J$2:$J$47,"Pass") | F28: =COUNTIFS(Log_Ejecucion!$D$2:$D$47,A28,Log_Ejecucion!$J$2:$J$47,"Fail")
A29: ACH | B29: =COUNTIF(Log_Ejecucion!$D$2:$D$47,A29) | C29: =COUNTIF(Bug_Tracker!$C$2:$C$41,A29) | D29: =IF(B29=0,0,C29/B29) | E29: =COUNTIFS(Log_Ejecucion!$D$2:$D$47,A29,Log_Ejecucion!$J$2:$J$47,"Pass") | F29: =COUNTIFS(Log_Ejecucion!$D$2:$D$47,A29,Log_Ejecucion!$J$2:$J$47,"Fail")
A30: Auditoría y reportes | B30: =COUNTIF(Log_Ejecucion!$D$2:$D$47,A30) | C30: =COUNTIF(Bug_Tracker!$C$2:$C$41,A30) | D30: =IF(B30=0,0,C30/B30) | E30: =COUNTIFS(Log_Ejecucion!$D$2:$D$47,A30,Log_Ejecucion!$J$2:$J$47,"Pass") | F30: =COUNTIFS(Log_Ejecucion!$D$2:$D$47,A30,Log_Ejecucion!$J$2:$J$47,"Fail")
A31: Dependencias de datos | B31: =COUNTIF(Log_Ejecucion!$D$2:$D$47,A31) | C31: =COUNTIF(Bug_Tracker!$C$2:$C$41,A31) | D31: =IF(B31=0,0,C31/B31) | E31: =COUNTIFS(Log_Ejecucion!$D$2:$D$47,A31,Log_Ejecucion!$J$2:$J$47,"Pass") | F31: =COUNTIFS(Log_Ejecucion!$D$2:$D$47,A31,Log_Ejecucion!$J$2:$J$47,"Fail")
A33: Histórico y ciclo 2 | B33: Valor | C33: Nota
A34: Ciclo 1 (19/10/2026): Pass / Fail | B34: 44 / 2 | C34: Log_Ciclo1_19-10; veredicto NO-GO
A35: Ciclo 1: Pass Rate | B35: 0.95652174 | C35: 95.7 %
A36: Ciclo 1: Altos abiertos | B36: 2 | C36: BUG-NEX-01, BUG-NEX-02
A37: Ciclo 2: aserciones automatizadas sin fallo | B37: 257 / 257 | C37: 184 peticiones: regresión 46 casos + re-prueba + preparación (Resumen_Ejecucion_Ciclo2.json)
A38: Ciclo 2: pruebas unitarias de autorización | B38: 26 / 26 | C38: Sin la corrección: 16 / 26 (02_Pruebas_Unitarias)
A39: Ciclo 2: defectos re-probados y cerrados | B39: 2 / 2 | C39: Re-prueba aprobada (confirmation testing)

Sheet Criterios_Salida
A1: Metrica_de_Calidad | B1: Objetivo_Planificado (MTP) | C1: Valor_Final_Obtenido | D1: Estado_Criterio | E1: Especialista_QA_Evaluador
A2: Pruebas críticas ejecutadas | B2: 100% de casos P1 ejecutados y con evidencia | C2: =Metricas_TSR!B13 | D2: =IF(Metricas_TSR!$B$8=0,"Pendiente",IF(Metricas_TSR!B13=1,"Cumplido","No cumplido")) | E2: Luis Contreras
A3: Defectos críticos abiertos | B3: 0 críticos abiertos; críticos corregidos con re-prueba aprobada | C3: =Metricas_TSR!B15 | D3: =IF(Metricas_TSR!$B$8=0,"Pendiente",IF(Metricas_TSR!B15=0,"Cumplido","No cumplido")) | E3: Luis Contreras
A4: Defectos altos abiertos | B4: Máximo 2 altos abiertos, con riesgo documentado, workaround y aceptación del PO | C4: =Metricas_TSR!B16 | D4: =IF(Metricas_TSR!$B$8=0,"Pendiente",IF(Metricas_TSR!B16=0,"Cumplido",IF(AND(Metricas_TSR!B16<=2,$C$13="Sí"),"Cumplido con aceptación PO","No cumplido"))) | E4: Luis Contreras
A5: Cobertura de requerimientos críticos | B5: 100% de REQ críticos trazados a al menos un caso | C5: =IF(COUNTIF(RTM_Final!$B$2:$B$19,"Crítica")=0,0,COUNTIFS(RTM_Final!$B$2:$B$19,"Crítica",RTM_Final!$H$2:$H$19,">0")/COUNTIF(RTM_Final!$B$2:$B$19,"Crítica")) | D5: =IF(C5=1,"Cumplido","No cumplido") | E5: Walter Rosales
A6: Porcentaje de ejecución | B6: >= 95% de casos planificados ejecutados | C6: =Metricas_TSR!B9 | D6: =IF(Metricas_TSR!$B$8=0,"Pendiente",IF(Metricas_TSR!B9>=0.95,"Cumplido","No cumplido")) | E6: Walter Rosales
A7: Tasa de éxito (Pass Rate) | B7: >= 90% de casos ejecutados en Pass (no estaba en el MTP; se adopta como métrica complementaria según la guía E3) | C7: =Metricas_TSR!B10 | D7: =IF(Metricas_TSR!$B$8=0,"Pendiente",IF(Metricas_TSR!B10>=0.9,"Cumplido","No cumplido")) | E7: Walter Rosales
A8: Integridad financiera | B8: 100% de escenarios P1 de depósitos/retiros/transferencias reconcilian saldo, movimiento y caja | C8: =IF(COUNTIF(Log_Ejecucion!$M$2:$M$47,"Financiero")=0,0,COUNTIFS(Log_Ejecucion!$M$2:$M$47,"Financiero",Log_Ejecucion!$J$2:$J$47,"Pass")/COUNTIF(Log_Ejecucion!$M$2:$M$47,"Financiero")) | D8: =IF(Metricas_TSR!$B$8=0,"Pendiente",IF(C8=1,"Cumplido","No cumplido")) | E8: Sergio Och
A9: Autorización | B9: 100% de endpoints P1 probados con usuario permitido y no permitido, sin cambios en intentos denegados | C9: =IF(COUNTIF(Log_Ejecucion!$M$2:$M$47,"Autorización")=0,0,COUNTIFS(Log_Ejecucion!$M$2:$M$47,"Autorización",Log_Ejecucion!$J$2:$J$47,"Pass")/COUNTIF(Log_Ejecucion!$M$2:$M$47,"Autorización")) | D9: =IF(Metricas_TSR!$B$8=0,"Pendiente",IF(C9=1,"Cumplido","No cumplido")) | E9: Anderson Ariana
A10: Regresión | B10: Smoke y regresión P1 aprobados en la misma build candidata | C10: Aprobada | D10: =IF(C10="Aprobada","Cumplido",IF(C10="No aprobada","No cumplido","Pendiente")) | E10: Luis Contreras
A13: Aceptación del PO para altos abiertos | B13: Solo aplica si hay ≤ 2 altos abiertos con riesgo documentado y workaround · Ciclo 2: no aplica (0 Altos abiertos). | C13: No

Sheet Veredicto
A1: Rol_en_el_Proyecto | B1: Nombre_del_Integrante | C1: Veredicto_Individual | D1: Observaciones_Tecnicas
A2: Líder de QA | B2: Luis Alejandro Contreras Paredez | C2: GO | D2: GO: 9 de 9 criterios cumplidos. BUG-NEX-01 y BUG-NEX-02 cerrados con re-prueba aprobada; regresión completa 46/46 Pass en la build corregida; 30/30 P1.
A3: Especialista QA – Funcional | B3: Walter Rene Rosales Hurtarte | C3: GO | D3: GO: Pass Rate 100 % (46/46). Clientes, cuentas y portal 13/13 Pass en la regresión del ciclo 2.
A4: Especialista QA – Técnico / Entornos | B4: Anderson Alexander Ariana Abadio | C4: GO | D4: GO: autorización 5/5 (100 %). BUG-NEX-01 re-probado: 9 rutas sin token → 401, 5 roles sin permiso → 403, accesos legítimos conservados, Mongo sin cambios.
A5: Especialista QA – Datos | B5: Sergio Eduardo Och Sunun | C5: GO | D5: GO: integridad financiera 9/9 con verificación SQL antes/después en los 46 casos. BUG-NEX-02 cerrado (achAprobadas 1, montoAch Q25). OBS-E3-01 sigue elevada al PO.
A6: VEREDICTO FINAL DEL EQUIPO | C6: =IF(COUNTIF(Criterios_Salida!$D$2:$D$10,"Pendiente")>0,"PENDIENTE",IF(COUNTIF(Criterios_Salida!$D$2:$D$10,"No cumplido")>0,"NO-GO","GO")) | D6: Regla del MTP: GO solo si todos los criterios de salida están en Cumplido; cualquier No cumplido = NO-GO. Veredicto del ciclo 2 (22/10/2026); sustituye al NO-GO del 19/10/2026.
A7: Fecha del veredicto | C7: 46317
A9: Acta del ciclo 1 (19/10/2026) — histórico
A10: Líder de QA | B10: Luis Alejandro Contreras Paredez | C10: NO-GO | D10: NO-GO: 2 defectos Altos abiertos sin aceptación del PO; regresión P1 no aprobada (TC-REQ03-002 sigue en Fail por BUG-NEX-01). P1 ejecutados 30/30 y ejecución 100 %.
A11: Especialista QA – Funcional | B11: Walter Rene Rosales Hurtarte | C11: NO-GO | D11: NO-GO: Pass Rate 95.7 % (44/46) cumple; clientes, cuentas y portal 13/13 Pass; se adhiere al NO-GO por los Altos abiertos.
A12: Especialista QA – Técnico / Entornos | B12: Anderson Alexander Ariana Abadio | C12: NO-GO | D12: NO-GO: BUG-NEX-01 confirmado (configuración ACH y escritura sin token); criterio de autorización 4/5 (80 %).
A13: Especialista QA – Datos | B13: Sergio Eduardo Och Sunun | C13: NO-GO | D13: NO-GO: integridad financiera 9/9 reconciliada; BUG-NEX-02 deja el reporte ACH incompleto y la caja admite efectivo esperado negativo (OBS-E3-01).
A14: VEREDICTO FINAL DEL EQUIPO | C14: NO-GO | D14: Regla del MTP: GO solo si todos los criterios de salida están en Cumplido; cualquier No cumplido = NO-GO.

Sheet Readiness
A1: ID | B1: Componente | C1: Configuración / URL | D1: Estado de verificación | E1: Evidencia | F1: Responsable
A2: RD-01 | B2: Contenedores QA | C2: docker compose bancoerp-e2-qa: frontend, internal-api, public-api, postgres, mongo, mock-bank | D2: APTO: 6 servicios running; postgres healthy | E2: Readiness_Log.txt; 04_Readiness_Observado.png | F2: Luis (Líder QA)
A3: RD-02 | B3: Frontend React | C3: http://localhost:13000/login | D3: APTO: HTTP 200 (text/html) | E3: 01_Frontend_QA_login_13000.png | F3: Walter (QA Funcional)
A4: RD-03 | B4: InternalAPI .NET | C4: http://localhost:15141/swagger/v1/swagger.json | D4: APTO: HTTP 200; 72 rutas | E4: 02_Swagger_InternalAPI_15141.png; OpenAPI_Interna.json | F4: Anderson (QA Técnico)
A5: RD-04 | B5: PublicAPI .NET | C5: http://localhost:15254/swagger/v1/swagger.json | D5: APTO: HTTP 200; 4 rutas | E5: 03_Swagger_PublicAPI_15254.png; OpenAPI_Publica.json | F5: Anderson (QA Técnico)
A6: RD-05 | B6: PostgreSQL 16 QA | C6: 127.0.0.1:15433 / bancoerp_e2_qa | D6: APTO: 8 usuarios, 1 000 clientes, 2 000 cuentas, 10 000 movimientos | E6: Readiness_Resultados.json (RD-05) | F6: Sergio (QA Datos)
A7: RD-06 | B7: Aislamiento de producción | C7: Red bancoerp-e2-qa_default; volúmenes propios; host postgres interno; puertos solo 127.0.0.1; código montado solo lectura | D7: APTO: sin destinos productivos configurados | E7: Readiness_Resultados.json (RD-06); docker-compose.qa.yml | F7: Anderson (QA Técnico)
A8: RD-07 | B8: MongoDB 8 (ACH) | C8: 127.0.0.1:17017 / bancoerp_e2_qa | D8: APTO: 5 bancos simulados locales, ninguno real | E8: Readiness_Log.txt (RD-07) | F8: Sergio (QA Datos)
A9: RD-08 | B9: Login interno | C9: POST :15141/api/auth/login (qa_cajero) | D9: APTO: HTTP 200; token presente (enmascarado) | E9: Readiness_Resultados.json (RD-08) | F9: Walter (QA Funcional)
A10: RD-09 | B10: Login externo | C10: POST :15254/api/external/auth/login | D10: APTO: HTTP 200; token presente (enmascarado) | E10: Readiness_Resultados.json (RD-09) | F10: Anderson (QA Técnico)
A11: RD-10 | B11: Cuenta destino sintética | C11: GET :15254/api/external/ach/cuentas/search/AH000000000001 | D11: APTO: HTTP 200; "Cuenta encontrada." | E11: Readiness_Resultados.json (RD-10) | F11: Sergio (QA Datos)
A12: RD-11 | B12: Control de autenticación | C12: GET :15141/api/clientes sin token | D12: APTO: HTTP 401 | E12: Readiness_Resultados.json (RD-11) | F12: Anderson (QA Técnico)
... A18: RD-16 (ciclo 2) | B18: Entorno de re-prueba | C18: docker compose -p bancoerp-e3-retest (volúmenes nuevos) + 009_ach_seed.sql | D18: APTO 22/10/2026: checklist 13/13 ok = t; smoke 5/5 HTTP 200; permisos ACH por rol verificados (OBS-RT-01 corregida) | E18: Re_Prueba_Cierre_E3/01_Entorno | F18: Luis (Líder QA)

Sheet Lecciones
A1: Área | B1: Qué pasó en el proyecto | C1: Qué haremos distinto
A2: Ambiente | B2: El docker-compose de desarrollo apuntaba a una BD remota; hubo que crear docker-compose.qa.yml con PostgreSQL aislado antes de poder ejecutar. | C2: Definir el ambiente QA aislado desde la Entrega 1, como entregable del plan.
A3: Requerimientos | B3: Cuatro reglas quedaron ambiguas (H-01 límite diario por canal, H-03 tolerancia de caja, H-04 timeout ACH, H-05 matriz de permisos) y bloquearon oráculos. | C3: Pedir al PO las reglas faltantes antes de diseñar; registrar cada decisión con fecha y responsable.
A4: Control de versiones | B4: Existieron dos versiones del paquete de la E2 (18 y 24 requerimientos) con IDs que no coincidían. | C4: Una sola fuente de verdad (Excel) de la que se generan Word, Postman y Mock Data; validar coherencia cruzada antes de entregar.
A5: Datos | B5: La carga masiva no servía para casos de frontera; se necesitó una capa de fixtures exacta e idempotente. | C5: Diseñar los datos por caso (Test Data Matrix) junto con el caso, no después.
A6: Seguridad | B6: El readiness detectó un endpoint de configuración accesible sin token antes de ejecutar la suite. | C6: Incluir un barrido de endpoints sin token en el smoke de cada build.
A7: Oráculos automatizados | B7: La aserción de TC-REQ16-001 solo buscaba "4000" y pasaba aunque el reporte omitía la ACH entrante. | C7: Comparar campo por campo; en el ciclo 2 TC-REQ16-001 valida 11 totales.
A8: Ambiente vs. producción | B8: El esquema QA omitió 009_ach_seed.sql; se notó cuando la corrección exigió permisos ACH (OBS-RT-01). | C8: Construir el esquema QA con la misma lista de scripts del despliegue a producción.
A9: Prevención de regresiones | B9: BUG-NEX-01 fue un [Authorize] olvidado en un controlador. | C9: Prueba unitaria que recorre todos los controladores y falla si un endpoint queda sin autorización.
A10: Re-prueba reproducible | B10: El ciclo 2 se ejecutó con scripts y se repitió desde cero tras cada interrupción. | C10: Mantener el kit de ejecución versionado junto a la colección.
